taipy/__init__.py
taipy/_entrypoint.py
taipy/_run.py
taipy/py.typed
taipy/version.json
taipy/version.py
taipy/event/__init__.py
taipy/event/_event_callback.py
taipy/event/_event_processor.py
taipy/event/event_processor.py
taipy/event/exceptions/__init__.py
taipy/event/exceptions/exceptions.py
taipy/gui_core/_GuiCoreLib.py
taipy/gui_core/__init__.py
taipy/gui_core/_adapters.py
taipy/gui_core/_context.py
taipy/gui_core/_init.py
taipy/gui_core/_utils.py
taipy/gui_core/filters.py
taipy/gui_core/viselements.json
taipy/gui_core/lib/taipy-gui-core.js
taipy-4.1.0.dist-info/licenses/LICENSE
taipy-4.1.0.dist-info/METADATA
taipy-4.1.0.dist-info/WHEEL
taipy-4.1.0.dist-info/entry_points.txt
taipy-4.1.0.dist-info/top_level.txt
taipy-4.1.0.dist-info/RECORD
