Metadata-Version: 2.4
Name: taipy
Version: 4.1.0
Summary: A 360° open-source platform from Python pilots to production-ready web apps.
Author-email: Avaiga <dev@taipy.io>
License: Apache-2.0
Project-URL: Homepage, https://www.taipy.io
Project-URL: Documentation, https://docs.taipy.io
Project-URL: Source, https://github.com/Avaiga/taipy
Project-URL: Download, https://pypi.org/project/taipy/#files
Project-URL: Tracker, https://github.com/Avaiga/taipy/issues
Project-URL: Security, https://github.com/Avaiga/taipy?tab=security-ov-file#readme
Keywords: taipy
Classifier: Intended Audience :: Developers
Classifier: License :: OSI Approved :: Apache Software License
Classifier: Natural Language :: English
Classifier: Programming Language :: Python :: 3
Classifier: Programming Language :: Python :: 3.9
Classifier: Programming Language :: Python :: 3.10
Classifier: Programming Language :: Python :: 3.11
Classifier: Programming Language :: Python :: 3.12
Requires-Python: <3.13,>=3.9
License-File: LICENSE
Requires-Dist: cookiecutter<=2.6.0,>=2.1.1
Requires-Dist: taipy-gui<4.2,>=4.1
Requires-Dist: taipy-rest<4.2,>=4.1
Requires-Dist: taipy-templates<4.2,>=4.1
Provides-Extra: ngrok
Requires-Dist: pyngrok<6.0,>=5.1; extra == "ngrok"
Provides-Extra: image
Requires-Dist: python-magic<0.5,>=0.4.24; extra == "image"
Requires-Dist: python-magic-bin<0.5,>=0.4.14; extra == "image"
Provides-Extra: rdp
Requires-Dist: rdp>=0.8; extra == "rdp"
Provides-Extra: arrow
Requires-Dist: pyarrow<19.0,>=16.0.0; extra == "arrow"
Provides-Extra: mssql
Requires-Dist: pyodbc>=4; extra == "mssql"
Provides-Extra: test
Requires-Dist: pytest>=6.0; extra == "test"
Dynamic: license-file
Dynamic: requires-dist
